cmem_plugin_pdf_extract/__init__.py
cmem_plugin_pdf_extract/doc/__init__.py
cmem_plugin_pdf_extract/doc/pdf_extract_doc.md
cmem_plugin_pdf_extract/extraction_strategies/__init__.py
cmem_plugin_pdf_extract/extraction_strategies/table_extraction_strategies.py
cmem_plugin_pdf_extract/extraction_strategies/text_extraction_strategies.py
cmem_plugin_pdf_extract/pdf-extract.svg
cmem_plugin_pdf_extract/pdf_extract.py
cmem_plugin_pdf_extract/utils.py
cmem_plugin_pdf_extract-1.1.0.dist-info/METADATA
cmem_plugin_pdf_extract-1.1.0.dist-info/WHEEL
cmem_plugin_pdf_extract-1.1.0.dist-info/licenses/LICENSE
cmem_plugin_pdf_extract-1.1.0.dist-info/RECORD
